<Panel class="sapUiSmallMargin padding-zero sapUiResponsiveMargin employee-panel">
              <HBox class="employee-card full-width">
                
                <!-- Employee Details -->
                <HBox class="desktop-view">
                  <VBox class="desktop-name-section">
                    <Title text="{directory>name}" level="H2" class="employee-name"/>
                    <Text text="{directory>designation}" class="employee-designation"/>
                    <Text text="{directory>work}" class="employee-work"/>
                  </VBox>

                  <HBox class="employee-details-row">
                    <Text text="ðŸ“¦ Unit: {directory>unit} / {directory>division}" class="employee-detail"/>
                  </HBox>

                  <HBox class="employee-details-row">
                    <Text text="ðŸ”¢ CUG: {directory>cug_number}" class="employee-detail cug-number"/>
                    <Text text="â˜Žï¸ Landline Office: {directory>landline_office}" class="employee-detail"/>
                    <Text text="â˜Žï¸ Landline Residence: {directory>landline_residence}" class="employee-detail"/>
                  </HBox>

                  <HBox class="employee-details-row">
                    <Text text="ðŸ“ž NLC Office No: {directory>nlc_number_office}" class="employee-detail"/>
                    <Text text="ðŸ“ž NLC Residence No: {directory>nlc_number_residence}" class="employee-detail"/>
                  </HBox>
                </HBox>

              </HBox>
            </Panel>